MANIFEST.in
README.md
setup.py
./hello/__init__.py
./hello/hello.py
mateusz_hello_application.egg-info/PKG-INFO
mateusz_hello_application.egg-info/SOURCES.txt
mateusz_hello_application.egg-info/dependency_links.txt
mateusz_hello_application.egg-info/top_level.txt