Metadata-Version: 1.0
Name: mateusz-hello-application
Version: 1.0.2
Summary: Application Hello by Mateusz
Home-page: UNKNOWN
Author: UNKNOWN
Author-email: UNKNOWN
License: UNKNOWN
Platform: UNKNOWN
